aliyunsdkiot/__init__.py
aliyunsdkiot/endpoint.py
aliyunsdkiot/request/__init__.py
aliyunsdkiot/request/v20180120/AddDataForApiSourceRequest.py
aliyunsdkiot/request/v20180120/AddDeviceToSharePromotionRequest.py
aliyunsdkiot/request/v20180120/AddPowerStationRequest.py
aliyunsdkiot/request/v20180120/AddShareTaskDeviceRequest.py
aliyunsdkiot/request/v20180120/AsyncRRpcRequest.py
aliyunsdkiot/request/v20180120/AttachDestinationRequest.py
aliyunsdkiot/request/v20180120/AttachParserDataSourceRequest.py
aliyunsdkiot/request/v20180120/BatchAddDataForApiSourceRequest.py
aliyunsdkiot/request/v20180120/BatchAddDeviceGroupRelationsRequest.py
aliyunsdkiot/request/v20180120/BatchAddThingTopoRequest.py
aliyunsdkiot/request/v20180120/BatchBindDeviceToEdgeInstanceWithDriverRequest.py
aliyunsdkiot/request/v20180120/BatchBindDevicesIntoProjectRequest.py
aliyunsdkiot/request/v20180120/BatchBindProductsIntoProjectRequest.py
aliyunsdkiot/request/v20180120/BatchCheckDeviceNamesRequest.py
aliyunsdkiot/request/v20180120/BatchCheckImportDeviceRequest.py
aliyunsdkiot/request/v20180120/BatchCheckVehicleDeviceRequest.py
aliyunsdkiot/request/v20180120/BatchClearEdgeInstanceDeviceConfigRequest.py
aliyunsdkiot/request/v20180120/BatchCreateSoundCodeLabelRequest.py
aliyunsdkiot/request/v20180120/BatchCreateSoundCodeLabelWithLabelsRequest.py
aliyunsdkiot/request/v20180120/BatchDeleteDeviceGroupRelationsRequest.py
aliyunsdkiot/request/v20180120/BatchDeleteEdgeInstanceChannelRequest.py
aliyunsdkiot/request/v20180120/BatchGetDeviceBindStatusRequest.py
aliyunsdkiot/request/v20180120/BatchGetDeviceStateRequest.py
aliyunsdkiot/request/v20180120/BatchGetEdgeDriverRequest.py
aliyunsdkiot/request/v20180120/BatchGetEdgeInstanceChannelRequest.py
aliyunsdkiot/request/v20180120/BatchGetEdgeInstanceDeviceChannelRequest.py
aliyunsdkiot/request/v20180120/BatchGetEdgeInstanceDeviceConfigRequest.py
aliyunsdkiot/request/v20180120/BatchGetEdgeInstanceDeviceDriverRequest.py
aliyun_python_sdk_iot-8.59.0.dist-info/LICENSE
aliyun_python_sdk_iot-8.59.0.dist-info/METADATA
aliyun_python_sdk_iot-8.59.0.dist-info/WHEEL
aliyun_python_sdk_iot-8.59.0.dist-info/top_level.txt
aliyun_python_sdk_iot-8.59.0.dist-info/RECORD
